cli.py
gui.py
generative_ai/__init__.py
generative_ai/metadata.json
generative_ai/py.typed
generative_ai/top_level.py
generative_ai/utils_top_level.py
generative_ai/dataset_generation/__init__.py
generative_ai/dataset_generation/orchestrate_generation.py
generative_ai/dataset_generation/step_1_generation.py
generative_ai/dataset_generation/step_2_generation.py
generative_ai/dataset_generation/utils_generation.py
generative_ai/information_retrieval/__init__.py
generative_ai/information_retrieval/orchestrate_retrieval.py
generative_ai/information_retrieval/step_1_retrieval.py
generative_ai/information_retrieval/step_2_retrieval.py
generative_ai/information_retrieval/step_3_retrieval.py
generative_ai/information_retrieval/utils_retrieval.py
query_package_documentation-0.0.3.dist-info/LICENSE
query_package_documentation-0.0.3.dist-info/METADATA
query_package_documentation-0.0.3.dist-info/WHEEL
query_package_documentation-0.0.3.dist-info/entry_points.txt
query_package_documentation-0.0.3.dist-info/top_level.txt
query_package_documentation-0.0.3.dist-info/RECORD
